metamusic/__init__.py
metamusic/app.py
metamusic/fetcher.py
metamusic/meta-music.desktop
metamusic/metamusic.png
metamusic/model.py
metamusic/static/index.html
metamusic/static/layout.html
metamusic/static/nofile.html
metamusic/static/process.html
metamusic/static/dist/Worker.js
metamusic/static/dist/bundle.js
metamusic/static/dist/css/bootstrap.css
metamusic/static/dist/css/bootstrap.min.css
metamusic/static/dist/css/bootstrap.min.css.map
metamusic/static/dist/css/bulma.css
metamusic/static/dist/css/bulma.css.map
metamusic/static/dist/css/main.css
metamusic/static/dist/css/style.css
metamusic/static/dist/img/error.png
metamusic/tests/__init__.py
metamusic/tests/test_metamusic.py
MetaMusic-1.1.7.2.dist-info/LICENSE
MetaMusic-1.1.7.2.dist-info/METADATA
MetaMusic-1.1.7.2.dist-info/WHEEL
MetaMusic-1.1.7.2.dist-info/entry_points.txt
MetaMusic-1.1.7.2.dist-info/top_level.txt
MetaMusic-1.1.7.2.dist-info/RECORD
