Metadata-Version: 2.1
Name: MetaMusic
Version: 1.1.7.2
Summary: Metamusic
Home-page: https://github.com/unique1o1/Meta-Music
Author: Yunik Maharjan
Author-email: yunik.maharjan@icloud.com
License: MIT
Platform: Linux
Platform: MacOS
Platform: Windows
Classifier: Environment :: Console
Classifier: Programming Language :: Python :: 3.6
Requires-Dist: attrs (==17.4.0)
Requires-Dist: beautifulsoup4 (==4.6.0)
Requires-Dist: bs4 (==0.0.1)
Requires-Dist: certifi (==2018.1.18)
Requires-Dist: chardet (==3.0.4)
Requires-Dist: click (==6.7)
Requires-Dist: eyeD3 (==0.8.4)
Requires-Dist: Flask (==0.12.2)
Requires-Dist: Flask-SQLAlchemy (==2.3.2)
Requires-Dist: idna (==2.6)
Requires-Dist: itsdangerous (==0.24)
Requires-Dist: Jinja2 (==2.10)
Requires-Dist: MarkupSafe (==1.0)
Requires-Dist: mutagen (==1.40.0)
Requires-Dist: numpy (==1.14.0)
Requires-Dist: pathlib (==1.0.1)
Requires-Dist: pluggy (==0.6.0)
Requires-Dist: psycopg2 (==2.7.4)
Requires-Dist: py (==1.5.2)
Requires-Dist: pytest (==3.4.2)
Requires-Dist: python-magic (==0.4.15)
Requires-Dist: requests (==2.18.4)
Requires-Dist: six (==1.11.0)
Requires-Dist: SQLAlchemy (==1.2.3)
Requires-Dist: urllib3 (==1.22)
Requires-Dist: Werkzeug (==0.14.1)
